ccfcsharp/__init__.py
ccfcsharp/__main__.py
ccfcsharp/class_fix.py
ccfcsharp/code_convention_fixer.py
ccfcsharp/declaration.py
ccfcsharp/declaration_type.py
ccfcsharp/identifier_dfa.py
ccfcsharp/interface_fix.py
ccfcsharp/keywords_constants.py
ccfcsharp/lexem.py
ccfcsharp/lexem_type.py
ccfcsharp/lexer.py
ccfcsharp/multiline_comment_dfa.py
ccfcsharp/naming_convention_fix.py
ccfcsharp/number_dfa.py
ccfcsharp/operator_dfa.py
ccfcsharp/punctuation_char_dfa.py
ccfcsharp/singleline_comment_dfa.py
ccfcsharp/string_dfa.py
ccfcsharp/whitespace_sequence_dfa.py
ccfcsharp-1.1.4.dist-info/METADATA
ccfcsharp-1.1.4.dist-info/WHEEL
ccfcsharp-1.1.4.dist-info/entry_points.txt
ccfcsharp-1.1.4.dist-info/top_level.txt
ccfcsharp-1.1.4.dist-info/RECORD
