Metadata-Version: 2.1
Name: ccfcsharp
Version: 1.1.4
Summary: C# code conventions analyzer and fixer
Home-page: https://github.com/MaiiaChudinova/univ_metaprogramming
Author: Maiia Chudinova
License: UNKNOWN
Platform: UNKNOWN
Requires-Dist: chardet
